topsis/__init__.py
topsis/topsis.py
Topsis_Girish_102003323-0.1.5.dist-info/LICENSE.txt
Topsis_Girish_102003323-0.1.5.dist-info/METADATA
Topsis_Girish_102003323-0.1.5.dist-info/WHEEL
Topsis_Girish_102003323-0.1.5.dist-info/entry_points.txt
Topsis_Girish_102003323-0.1.5.dist-info/top_level.txt
Topsis_Girish_102003323-0.1.5.dist-info/RECORD
