Metadata-Version: 2.1
Name: Topsis-Girish-102003323
Version: 0.1.5
Summary: This package can be used to calculate the topsis score of multiple component data and rank them accordingly
Home-page: UNKNOWN
Author: Girish Gupta
Author-email: girish2001gupta@gmail.com
License: MIT
Project-URL: Source, https://github.com/girishnaman/topsis-package
Keywords: TOPSIS
Platform: UNKNOWN
Classifier: Programming Language :: Python :: 3
Classifier: License :: OSI Approved :: MIT License
Classifier: Operating System :: OS Independent
Classifier: Programming Language :: Python :: 3
Classifier: Programming Language :: Python :: 3.4
Classifier: Programming Language :: Python :: 3.5
Classifier: Programming Language :: Python :: 3.6
Requires-Dist: pandas
Requires-Dist: numpy
Requires-Dist: sklearn
